Workbook

Sheet Data
A1: request_id | B1: request_year | C1: request_status | D1: request_length_words | E1: dominant_topic | F1: dominant_topic_label | G1: Typology of Administration | H1: sentiment_z | I1: ASP_level | J1: sex (requester) | K1: sex (respondent)
A2: frais_de_voyage_des_cabinets_du_4 | B2: 2017 | C2: Not successful | D2: 84 | E2: T3 | F2: T3: Police & administrative authority legality | G2: 1. Local Territorial Authorities and Public Local Entities | H2: 2.354266 | I2: 4 | J2: FEMALE | K2: UNKNOWN
A3: sau_msi_drohme_procedure_dattrib | B3: 2017 | C3: Successful | D3: 73 | E3: T1 | F3: T1: Public finance oversight | G3: 5. Sectoral Agencies, Intermunicipal Organizations, and Specialized Bodies | H3: -0.08142632 | I3: 3 | J3: MALE | K3: FEMALE
A4: travaux_publics_2001_2016_3 | B4: 2017 | C4: Not successful | D4: 73 | E4: T2 | F4: T2: Urban planning & neighbourhood issues | G4: 1. Local Territorial Authorities and Public Local Entities | H4: -0.78015241 | I4: 2 | J4: FEMALE | K4: MALE
A5: composition_des_cabinets_du_bour_18 | B5: 2017 | C5: Successful | D5: 153 | E5: T1 | F5: T1: Public finance oversight | G5: 1. Local Territorial Authorities and Public Local Entities | H5: -0.38180006 | I5: 3 | J5: FEMALE | K5: MALE
A6: transparence_des_mandats_liste_d_15 | B6: 2016 | C6: Successful | D6: 87 | E6: T4 | F6: T4: Council deliberations & transparency | G6: 1. Local Territorial Authorities and Public Local Entities | H6: 0.12592813 | I6: 4 | J6: MALE | K6: FEMALE
A7: demande_de_la_liste_complete_des_2 | B7: 2017 | C7: Successful | D7: 61 | E7: T2 | F7: T2: Urban planning & neighbourhood issues | G7: 1. Local Territorial Authorities and Public Local Entities | H7: 1.2071335 | I7: 2 | J7: MALE | K7: FEMALE
A8: justificatif_du_retard_de_rectif | B8: 2017 | C8: Asleep | D8: 179 | E8: T2 | F8: T2: Urban planning & neighbourhood issues | G8: 9. Social Housing and Public Residential Institutions | H8: -0.44312731 | I8: 2 | J8: FEMALE | K8: NO_RESPONSE
A9: interdiction_de_circulation_des | B9: 2017 | C9: Asleep | D9: 95 | E9: T1 | F9: T1: Public finance oversight | G9: 10. Police, Defense, and Public Safety Structures | H9: -0.3265328 | I9: 3 | J9: FEMALE | K9: FEMALE
A10: conseil_communal_seance_du_12_ju | B10: 2017 | C10: Successful | D10: 52 | E10: T6 | F10: T6: Governance & municipal finance analysis | G10: 1. Local Territorial Authorities and Public Local Entities | H10: -0.75255121 | I10: 3 | J10: MALE | K10: UNKNOWN
A11: titre_honorifique_de_directeur_d | B11: 2018 | C11: Not successful | D11: 163 | E11: T1 | F11: T1: Public finance oversight | G11: 3. Federal Institutions and National Government Bodies | H11: 0.61922807 | I11: 3 | J11: MALE | K11: MALE
A12: composition_des_cabinets_du_bour_10 | B12: 2017 | C12: Not successful | D12: 151 | E12: T1 | F12: T1: Public finance oversight | G12: 1. Local Territorial Authorities and Public Local Entities | H12: -0.08142632 | I12: 3 | J12: FEMALE | K12: UNKNOWN
A13: liste_des_veterinaires | B13: 2017 | C13: Not successful | D13: 49 | E13: T1 | F13: T1: Public finance oversight | G13: 6. Regulatory, Supervisory, and Oversight Authorities | H13: 0.22729113 | I13: 3 | J13: UNKNOWN | K13: MALE
... A4266: enquete_du_journal_lesoir_projet_43 | B4266: 2021 | C4266: Asleep | D4266: 369 | E4266: T6 | F4266: T6: Governance & municipal finance analysis | G4266: 1. Local Territorial Authorities and Public Local Entities | H4266: 0.69311782 | I4266: 3 | J4266: MALE | K4266: FEMALE

Sheet Analysis
A1: CROSS-GENDER ANALYSIS
A3: SECTION 1: Dataset Overview
A4: Metric | B4: Count | C4: Formula
A5: Total requests | B5: =COUNTA(Data!A2:A10000) -> 4265 | C5: Counts all non-empty request_id cells
A6: Requests with response (col K not blank) | B6: =COUNTA(Data!K2:L10000) -> 4265 | C6: Counts non-empty cells in sex (respondent)
A7: Requests WITHOUT response (col K blank) | B7: =COUNTBLANK(Data!K2:L4274) -> 4281 | C7: Blank cells in col K (rows 2-4274)
A9: Requester gender known (col J not UNKNOWN*) | B9: =COUNTIFS(Data!J2:J10000,"MALE")+COUNTIFS(Data!J2:J10000,"FEMALE") -> 3825 | C9: MALE + FEMALE in col J
A10: Requester gender UNKNOWN (col J) | B10: =COUNTIFS(Data!J2:J10000,"UNKNOWN") -> 440 | C10: UNKNOWN in col J
A11: Requester gender known BUT no response data (col K blank) | B11: =SUMPRODUCT((Data!J2:J4274<>"UNKNOWN")*(Data!K2:L4274=""))+SUMPRODUCT((Data!J2:J4274<>"UNKNOWN")*(ISBLANK(Data!K2:L4274))) -> 7682 | C11: Requester is MALE or FEMALE but col K is empty — no response to analyze
A12: Respondent gender known (col K is MALE or FEMALE) | B12: =COUNTIFS(Data!K2:L10000,"MALE")+COUNTIFS(Data!K2:L10000,"FEMALE") -> 1293 | C12: MALE + FEMALE inferred in col K
A13: Respondent gender UNKNOWN (any UNKNOWN category in col K) | B13: =COUNTIFS(Data!K2:L10000,"UNKNOWN*") -> 1218 | C13: All UNKNOWN variants in col K
A15: SECTION 2: Requests with BOTH genders known
A16: (Among requests that have a response, i.e. col K not blank)
A18: Metric | B18: Count | C18: % of responded requests
A19: Both requester AND respondent gender known | B19: =SUMPRODUCT((Data!J2:J4274<>"UNKNOWN")*(Data!K2:L4274<>"")*(LEFT(Data!K2:L4274,7)<>"UNKNOWN")) -> 2714 | C19: =IF(B6>0,B19/B6,"N/A") -> 0.63634232
A20: Requester known, respondent UNKNOWN | B20: =SUMPRODUCT((Data!J2:J4274<>"UNKNOWN")*(Data!K2:L4274<>"")*(LEFT(Data!K2:L4274,7)="UNKNOWN")) -> 1111 | C20: =IF(B6>0,B20/B6,"N/A") -> 0.26049238
A21: Requester UNKNOWN, respondent known | B21: =SUMPRODUCT((Data!J2:J4274="UNKNOWN")*(Data!K2:L4274<>"")*(LEFT(Data!K2:L4274,7)<>"UNKNOWN")) -> 333 | C21: =IF(B6>0,B21/B6,"N/A") -> 0.078077374
A22: Both UNKNOWN | B22: =SUMPRODUCT((Data!J2:J4274="UNKNOWN")*(Data!K2:L4274<>"")*(LEFT(Data!K2:L4274,7)="UNKNOWN")) -> 107 | C22: =IF(B6>0,B22/B6,"N/A") -> 0.025087925
A23: CHECK: sum should equal responded requests (B6) | B23: =B19+B20+B21+B22 -> 4265 | C23: =IF(B23=B6,"OK","MISMATCH!") -> OK
A25: SECTION 3: Cross-tabulation (Requester × Respondent gender)
A26: Only among the 2,517 requests that received a response. Each cell = number of requests where requester is [row gender] AND respondent is [column gender].
A28: Requester ↓ Respondent → | B28: Respondent: MALE | C28: Respondent: FEMALE | D28: Respondent: UNKNOWN* | E28: Row Total
A29: Requester: MALE | B29: =SUMPRODUCT((Data!J2:J4274="MALE")*(Data!K2:L4274="MALE")) -> 458 | C29: =SUMPRODUCT((Data!J2:J4274="MALE")*(Data!K2:L4274="FEMALE")) -> 338 | D29: =SUMPRODUCT((Data!J2:J4274="MALE")*(Data!K2:L4274<>"")*(LEFT(Data!K2:L4274,7)="UNKNOWN")) -> 767 | E29: =B29+C29+D29 -> 1563
A30: Requester: FEMALE | B30: =SUMPRODUCT((Data!J2:J4274="FEMALE")*(Data!K2:L4274="MALE")) -> 205 | C30: =SUMPRODUCT((Data!J2:J4274="FEMALE")*(Data!K2:L4274="FEMALE")) -> 200 | D30: =SUMPRODUCT((Data!J2:J4274="FEMALE")*(Data!K2:L4274<>"")*(LEFT(Data!K2:L4274,7)="UNKNOWN")) -> 344 | E30: =B30+C30+D30 -> 749
A31: Requester: UNKNOWN | B31: =SUMPRODUCT((Data!J2:J4274="UNKNOWN")*(Data!K2:L4274="MALE")) -> 52 | C31: =SUMPRODUCT((Data!J2:J4274="UNKNOWN")*(Data!K2:L4274="FEMALE")) -> 40 | D31: =SUMPRODUCT((Data!J2:J4274="UNKNOWN")*(Data!K2:L4274<>"")*(LEFT(Data!K2:L4274,7)="UNKNOWN")) -> 107 | E31: =B31+C31+D31 -> 199
A32: Column Total | B32: =B29+B30+B31 -> 715 | C32: =C29+C30+C31 -> 578 | D32: =D29+D30+D31 -> 1218 | E32: =E29+E30+E31 -> 2511
A35: SECTION 4: Respondent gender by requester gender — Does your gender affect who handles your request?
A36: Only requests with BOTH genders known (n=1,215). Each row: given requester gender, what % of respondents are male vs female? Rows sum to 100%.
A38: ALL TOPICS COMBINED
A39: Interaction | B39: Count | C39: % within requester gender | D39: Visual
A40: Male requester → Male respondent | B40: =SUMPRODUCT((Data!J2:J4274="MALE")*(Data!K2:L4274="MALE")) -> 458 | C40: =IF((B40+B41)>0, B40/(B40+B41), 0) -> 0.57537688 | D40: =REPT("█",ROUND(B40/MAX(B40:B43)*20,0)) -> ████████████████████
A41: Male requester → Female respondent | B41: =SUMPRODUCT((Data!J2:J4274="MALE")*(Data!K2:L4274="FEMALE")) -> 338 | C41: =IF((B40+B41)>0, B41/(B40+B41), 0) -> 0.42462312 | D41: =REPT("█",ROUND(B41/MAX(B40:B43)*20,0)) -> ███████████████
A42: Female requester → Male respondent | B42: =SUMPRODUCT((Data!J2:J4274="FEMALE")*(Data!K2:L4274="MALE")) -> 205 | C42: =IF((B42+B43)>0, B42/(B42+B43), 0) -> 0.50617284 | D42: =REPT("█",ROUND(B42/MAX(B40:B43)*20,0)) -> █████████
A43: Female requester → Female respondent | B43: =SUMPRODUCT((Data!J2:J4274="FEMALE")*(Data!K2:L4274="FEMALE")) -> 200 | C43: =IF((B42+B43)>0, B43/(B42+B43), 0) -> 0.49382716 | D43: =REPT("█",ROUND(B43/MAX(B40:B43)*20,0)) -> █████████
A44: Total known pairs | B44: =B40+B41+B42+B43 -> 1201
A47: BREAKDOWN BY TOPIC
A49: T1: Public finance oversight
A50: Interaction | B50: Count | C50: % within requester gender | D50: Visual
A51: Male requester → Male respondent | B51: =SUMPRODUCT((Data!E2:E4274="T1")*(Data!J2:J4274="MALE")*(Data!K2:L4274="MALE")) -> 160 | C51: =IF((B51+B52)>0, B51/(B51+B52), 0) -> 0.62015504 | D51: =IF(MAX(B51:B54)>0,REPT("█",ROUND(B51/MAX(B51:B54)*20,0)),"") -> ████████████████████
A52: Male requester → Female respondent | B52: =SUMPRODUCT((Data!E2:E4274="T1")*(Data!J2:J4274="MALE")*(Data!K2:L4274="FEMALE")) -> 98 | C52: =IF((B51+B52)>0, B52/(B51+B52), 0) -> 0.37984496 | D52: =IF(MAX(B51:B54)>0,REPT("█",ROUND(B52/MAX(B51:B54)*20,0)),"") -> ████████████
A53: Female requester → Male respondent | B53: =SUMPRODUCT((Data!E2:E4274="T1")*(Data!J2:J4274="FEMALE")*(Data!K2:L4274="MALE")) -> 52 | C53: =IF((B53+B54)>0, B53/(B53+B54), 0) -> 0.55913978 | D53: =IF(MAX(B51:B54)>0,REPT("█",ROUND(B53/MAX(B51:B54)*20,0)),"") -> ███████
A54: Female requester → Female respondent | B54: =SUMPRODUCT((Data!E2:E4274="T1")*(Data!J2:J4274="FEMALE")*(Data!K2:L4274="FEMALE")) -> 41 | C54: =IF((B53+B54)>0, B54/(B53+B54), 0) -> 0.44086022 | D54: =IF(MAX(B51:B54)>0,REPT("█",ROUND(B54/MAX(B51:B54)*20,0)),"") -> █████
A55: Total known pairs | B55: =B51+B52+B53+B54 -> 351
A57: T2: Urban planning & neighbourhood issues
A58: Interaction | B58: Count | C58: % within requester gender | D58: Visual
A59: Male requester → Male respondent | B59: =SUMPRODUCT((Data!E2:E4274="T2")*(Data!J2:J4274="MALE")*(Data!K2:L4274="MALE")) -> 78 | C59: =IF((B59+B60)>0, B59/(B59+B60), 0) -> 0.52348993 | D59: =IF(MAX(B59:B62)>0,REPT("█",ROUND(B59/MAX(B59:B62)*20,0)),"") -> ████████████████████
A60: Male requester → Female respondent | B60: =SUMPRODUCT((Data!E2:E4274="T2")*(Data!J2:J4274="MALE")*(Data!K2:L4274="FEMALE")) -> 71 | C60: =IF((B59+B60)>0, B60/(B59+B60), 0) -> 0.47651007 | D60: =IF(MAX(B59:B62)>0,REPT("█",ROUND(B60/MAX(B59:B62)*20,0)),"") -> ██████████████████
A61: Female requester → Male respondent | B61: =SUMPRODUCT((Data!E2:E4274="T2")*(Data!J2:J4274="FEMALE")*(Data!K2:L4274="MALE")) -> 43 | C61: =IF((B61+B62)>0, B61/(B61+B62), 0) -> 0.58108108 | D61: =IF(MAX(B59:B62)>0,REPT("█",ROUND(B61/MAX(B59:B62)*20,0)),"") -> ███████████
A62: Female requester → Female respondent | B62: =SUMPRODUCT((Data!E2:E4274="T2")*(Data!J2:J4274="FEMALE")*(Data!K2:L4274="FEMALE")) -> 31 | C62: =IF((B61+B62)>0, B62/(B61+B62), 0) -> 0.41891892 | D62: =IF(MAX(B59:B62)>0,REPT("█",ROUND(B62/MAX(B59:B62)*20,0)),"") -> ████████
A63: Total known pairs | B63: =B59+B60+B61+B62 -> 223
A65: T3: Police & administrative authority legality
A66: Interaction | B66: Count | C66: % within requester gender | D66: Visual
A67: Male requester → Male respondent | B67: =SUMPRODUCT((Data!E2:E4274="T3")*(Data!J2:J4274="MALE")*(Data!K2:L4274="MALE")) -> 53 | C67: =IF((B67+B68)>0, B67/(B67+B68), 0) -> 0.6091954 | D67: =IF(MAX(B67:B70)>0,REPT("█",ROUND(B67/MAX(B67:B70)*20,0)),"") -> ████████████████████
A68: Male requester → Female respondent | B68: =SUMPRODUCT((Data!E2:E4274="T3")*(Data!J2:J4274="MALE")*(Data!K2:L4274="FEMALE")) -> 34 | C68: =IF((B67+B68)>0, B68/(B67+B68), 0) -> 0.3908046 | D68: =IF(MAX(B67:B70)>0,REPT("█",ROUND(B68/MAX(B67:B70)*20,0)),"") -> █████████████
A69: Female requester → Male respondent | B69: =SUMPRODUCT((Data!E2:E4274="T3")*(Data!J2:J4274="FEMALE")*(Data!K2:L4274="MALE")) -> 11 | C69: =IF((B69+B70)>0, B69/(B69+B70), 0) -> 0.57894737 | D69: =IF(MAX(B67:B70)>0,REPT("█",ROUND(B69/MAX(B67:B70)*20,0)),"") -> ████
A70: Female requester → Female respondent | B70: =SUMPRODUCT((Data!E2:E4274="T3")*(Data!J2:J4274="FEMALE")*(Data!K2:L4274="FEMALE")) -> 8 | C70: =IF((B69+B70)>0, B70/(B69+B70), 0) -> 0.42105263 | D70: =IF(MAX(B67:B70)>0,REPT("█",ROUND(B70/MAX(B67:B70)*20,0)),"") -> ███
A71: Total known pairs | B71: =B67+B68+B69+B70 -> 106
A73: T4: Council deliberations & transparency
A74: Interaction | B74: Count | C74: % within requester gender | D74: Visual
A75: Male requester → Male respondent | B75: =SUMPRODUCT((Data!E2:E4274="T4")*(Data!J2:J4274="MALE")*(Data!K2:L4274="MALE")) -> 52 | C75: =IF((B75+B76)>0, B75/(B75+B76), 0) -> 0.56521739 | D75: =IF(MAX(B75:B78)>0,REPT("█",ROUND(B75/MAX(B75:B78)*20,0)),"") -> ████████████████████
A76: Male requester → Female respondent | B76: =SUMPRODUCT((Data!E2:E4274="T4")*(Data!J2:J4274="MALE")*(Data!K2:L4274="FEMALE")) -> 40 | C76: =IF((B75+B76)>0, B76/(B75+B76), 0) -> 0.43478261 | D76: =IF(MAX(B75:B78)>0,REPT("█",ROUND(B76/MAX(B75:B78)*20,0)),"") -> ███████████████
A77: Female requester → Male respondent | B77: =SUMPRODUCT((Data!E2:E4274="T4")*(Data!J2:J4274="FEMALE")*(Data!K2:L4274="MALE")) -> 23 | C77: =IF((B77+B78)>0, B77/(B77+B78), 0) -> 0.58974359 | D77: =IF(MAX(B75:B78)>0,REPT("█",ROUND(B77/MAX(B75:B78)*20,0)),"") -> █████████
A78: Female requester → Female respondent | B78: =SUMPRODUCT((Data!E2:E4274="T4")*(Data!J2:J4274="FEMALE")*(Data!K2:L4274="FEMALE")) -> 16 | C78: =IF((B77+B78)>0, B78/(B77+B78), 0) -> 0.41025641 | D78: =IF(MAX(B75:B78)>0,REPT("█",ROUND(B78/MAX(B75:B78)*20,0)),"") -> ██████
A79: Total known pairs | B79: =B75+B76+B77+B78 -> 131
A81: T5: Public procurement & administrative policing
A82: Interaction | B82: Count | C82: % within requester gender | D82: Visual
A83: Male requester → Male respondent | B83: =SUMPRODUCT((Data!E2:E4274="T5")*(Data!J2:J4274="MALE")*(Data!K2:L4274="MALE")) -> 18 | C83: =IF((B83+B84)>0, B83/(B83+B84), 0) -> 0.6 | D83: =IF(MAX(B83:B86)>0,REPT("█",ROUND(B83/MAX(B83:B86)*20,0)),"") -> ████
A84: Male requester → Female respondent | B84: =SUMPRODUCT((Data!E2:E4274="T5")*(Data!J2:J4274="MALE")*(Data!K2:L4274="FEMALE")) -> 12 | C84: =IF((B83+B84)>0, B84/(B83+B84), 0) -> 0.4 | D84: =IF(MAX(B83:B86)>0,REPT("█",ROUND(B84/MAX(B83:B86)*20,0)),"") -> ███
A85: Female requester → Male respondent | B85: =SUMPRODUCT((Data!E2:E4274="T5")*(Data!J2:J4274="FEMALE")*(Data!K2:L4274="MALE")) -> 66 | C85: =IF((B85+B86)>0, B85/(B85+B86), 0) -> 0.44594595 | D85: =IF(MAX(B83:B86)>0,REPT("█",ROUND(B85/MAX(B83:B86)*20,0)),"") -> ████████████████
A86: Female requester → Female respondent | B86: =SUMPRODUCT((Data!E2:E4274="T5")*(Data!J2:J4274="FEMALE")*(Data!K2:L4274="FEMALE")) -> 82 | C86: =IF((B85+B86)>0, B86/(B85+B86), 0) -> 0.55405405 | D86: =IF(MAX(B83:B86)>0,REPT("█",ROUND(B86/MAX(B83:B86)*20,0)),"") -> ████████████████████
A87: Total known pairs | B87: =B83+B84+B85+B86 -> 178
A89: T6: Governance & municipal finance analysis
A90: Interaction | B90: Count | C90: % within requester gender | D90: Visual
A91: Male requester → Male respondent | B91: =SUMPRODUCT((Data!E2:E4274="T6")*(Data!J2:J4274="MALE")*(Data!K2:L4274="MALE")) -> 97 | C91: =IF((B91+B92)>0, B91/(B91+B92), 0) -> 0.53888889 | D91: =IF(MAX(B91:B94)>0,REPT("█",ROUND(B91/MAX(B91:B94)*20,0)),"") -> ████████████████████
A92: Male requester → Female respondent | B92: =SUMPRODUCT((Data!E2:E4274="T6")*(Data!J2:J4274="MALE")*(Data!K2:L4274="FEMALE")) -> 83 | C92: =IF((B91+B92)>0, B92/(B91+B92), 0) -> 0.46111111 | D92: =IF(MAX(B91:B94)>0,REPT("█",ROUND(B92/MAX(B91:B94)*20,0)),"") -> █████████████████
A93: Female requester → Male respondent | B93: =SUMPRODUCT((Data!E2:E4274="T6")*(Data!J2:J4274="FEMALE")*(Data!K2:L4274="MALE")) -> 10 | C93: =IF((B93+B94)>0, B93/(B93+B94), 0) -> 0.3125 | D93: =IF(MAX(B91:B94)>0,REPT("█",ROUND(B93/MAX(B91:B94)*20,0)),"") -> ██
A94: Female requester → Female respondent | B94: =SUMPRODUCT((Data!E2:E4274="T6")*(Data!J2:J4274="FEMALE")*(Data!K2:L4274="FEMALE")) -> 22 | C94: =IF((B93+B94)>0, B94/(B93+B94), 0) -> 0.6875 | D94: =IF(MAX(B91:B94)>0,REPT("█",ROUND(B94/MAX(B91:B94)*20,0)),"") -> █████
A95: Total known pairs | B95: =B91+B92+B93+B94 -> 212
A97: SECTION 5: Request outcome by gender combo — What happens when they interact?
A98: Only requests with BOTH genders known (n=1,215). Each row: given this gender combo, what % of requests were Successful / Not successful / Asleep? Rows sum to 100%.
A100: ALL TOPICS COMBINED
A101: Gender combo | B101: Total | C101: Successful | D101: % Successful | E101: Not successful | F101: % Not succ. | G101: Asleep | H101: % Asleep
A102: Male req. → Male resp. | B102: =SUMPRODUCT((Data!J2:J4274="MALE")*(Data!K2:L4274="MALE")) -> 458 | C102: =SUMPRODUCT((Data!J2:J4274="MALE")*(Data!K2:L4274="MALE")*(Data!C2:C4274="Successful")) -> 267 | D102: =IF(B102>0,C102/B102,0) -> 0.58296943 | E102: =SUMPRODUCT((Data!J2:J4274="MALE")*(Data!K2:L4274="MALE")*(Data!C2:C4274="Not successful")) -> 91 | F102: =IF(B102>0,E102/B102,0) -> 0.19868996 | G102: =SUMPRODUCT((Data!J2:J4274="MALE")*(Data!K2:L4274="MALE")*(Data!C2:C4274="Asleep")) -> 100 | H102: =IF(B102>0,G102/B102,0) -> 0.21834061
A103: Male req. → Female resp. | B103: =SUMPRODUCT((Data!J2:J4274="MALE")*(Data!K2:L4274="FEMALE")) -> 338 | C103: =SUMPRODUCT((Data!J2:J4274="MALE")*(Data!K2:L4274="FEMALE")*(Data!C2:C4274="Successful")) -> 188 | D103: =IF(B103>0,C103/B103,0) -> 0.55621302 | E103: =SUMPRODUCT((Data!J2:J4274="MALE")*(Data!K2:L4274="FEMALE")*(Data!C2:C4274="Not successful")) -> 82 | F103: =IF(B103>0,E103/B103,0) -> 0.24260355 | G103: =SUMPRODUCT((Data!J2:J4274="MALE")*(Data!K2:L4274="FEMALE")*(Data!C2:C4274="Asleep")) -> 68 | H103: =IF(B103>0,G103/B103,0) -> 0.20118343
A104: Female req. → Male resp. | B104: =SUMPRODUCT((Data!J2:J4274="FEMALE")*(Data!K2:L4274="MALE")) -> 205 | C104: =SUMPRODUCT((Data!J2:J4274="FEMALE")*(Data!K2:L4274="MALE")*(Data!C2:C4274="Successful")) -> 104 | D104: =IF(B104>0,C104/B104,0) -> 0.50731707 | E104: =SUMPRODUCT((Data!J2:J4274="FEMALE")*(Data!K2:L4274="MALE")*(Data!C2:C4274="Not successful")) -> 39 | F104: =IF(B104>0,E104/B104,0) -> 0.1902439 | G104: =SUMPRODUCT((Data!J2:J4274="FEMALE")*(Data!K2:L4274="MALE")*(Data!C2:C4274="Asleep")) -> 62 | H104: =IF(B104>0,G104/B104,0) -> 0.30243902
A105: Female req. → Female resp. | B105: =SUMPRODUCT((Data!J2:J4274="FEMALE")*(Data!K2:L4274="FEMALE")) -> 200 | C105: =SUMPRODUCT((Data!J2:J4274="FEMALE")*(Data!K2:L4274="FEMALE")*(Data!C2:C4274="Successful")) -> 108 | D105: =IF(B105>0,C105/B105,0) -> 0.54 | E105: =SUMPRODUCT((Data!J2:J4274="FEMALE")*(Data!K2:L4274="FEMALE")*(Data!C2:C4274="Not successful")) -> 33 | F105: =IF(B105>0,E105/B105,0) -> 0.165 | G105: =SUMPRODUCT((Data!J2:J4274="FEMALE")*(Data!K2:L4274="FEMALE")*(Data!C2:C4274="Asleep")) -> 59 | H105: =IF(B105>0,G105/B105,0) -> 0.295
A108: BREAKDOWN BY TOPIC
A110: T1: Public finance oversight
A111: Gender combo | B111: Total | C111: Successful | D111: % Successful | E111: Not successful | F111: % Not succ. | G111: Asleep | H111: % Asleep
A112: Male req. → Male resp. | B112: =SUMPRODUCT((Data!E2:E4274="T1")*(Data!J2:J4274="MALE")*(Data!K2:L4274="MALE")) -> 160 | C112: =SUMPRODUCT((Data!E2:E4274="T1")*(Data!J2:J4274="MALE")*(Data!K2:L4274="MALE")*(Data!C2:C4274="Successful")) -> 97 | D112: =IF(B112>0,C112/B112,0) -> 0.60625 | E112: =SUMPRODUCT((Data!E2:E4274="T1")*(Data!J2:J4274="MALE")*(Data!K2:L4274="MALE")*(Data!C2:C4274="Not successful")) -> 31 | F112: =IF(B112>0,E112/B112,0) -> 0.19375 | G112: =SUMPRODUCT((Data!E2:E4274="T1")*(Data!J2:J4274="MALE")*(Data!K2:L4274="MALE")*(Data!C2:C4274="Asleep")) -> 32 | H112: =IF(B112>0,G112/B112,0) -> 0.2
A113: Male req. → Female resp. | B113: =SUMPRODUCT((Data!E2:E4274="T1")*(Data!J2:J4274="MALE")*(Data!K2:L4274="FEMALE")) -> 98 | C113: =SUMPRODUCT((Data!E2:E4274="T1")*(Data!J2:J4274="MALE")*(Data!K2:L4274="FEMALE")*(Data!C2:C4274="Successful")) -> 59 | D113: =IF(B113>0,C113/B113,0) -> 0.60204082 | E113: =SUMPRODUCT((Data!E2:E4274="T1")*(Data!J2:J4274="MALE")*(Data!K2:L4274="FEMALE")*(Data!C2:C4274="Not successful")) -> 22 | F113: =IF(B113>0,E113/B113,0) -> 0.2244898 | G113: =SUMPRODUCT((Data!E2:E4274="T1")*(Data!J2:J4274="MALE")*(Data!K2:L4274="FEMALE")*(Data!C2:C4274="Asleep")) -> 17 | H113: =IF(B113>0,G113/B113,0) -> 0.17346939
A114: Female req. → Male resp. | B114: =SUMPRODUCT((Data!E2:E4274="T1")*(Data!J2:J4274="FEMALE")*(Data!K2:L4274="MALE")) -> 52 | C114: =SUMPRODUCT((Data!E2:E4274="T1")*(Data!J2:J4274="FEMALE")*(Data!K2:L4274="MALE")*(Data!C2:C4274="Successful")) -> 36 | D114: =IF(B114>0,C114/B114,0) -> 0.69230769 | E114: =SUMPRODUCT((Data!E2:E4274="T1")*(Data!J2:J4274="FEMALE")*(Data!K2:L4274="MALE")*(Data!C2:C4274="Not successful")) -> 6 | F114: =IF(B114>0,E114/B114,0) -> 0.11538462 | G114: =SUMPRODUCT((Data!E2:E4274="T1")*(Data!J2:J4274="FEMALE")*(Data!K2:L4274="MALE")*(Data!C2:C4274="Asleep")) -> 10 | H114: =IF(B114>0,G114/B114,0) -> 0.19230769
A115: Female req. → Female resp. | B115: =SUMPRODUCT((Data!E2:E4274="T1")*(Data!J2:J4274="FEMALE")*(Data!K2:L4274="FEMALE")) -> 41 | C115: =SUMPRODUCT((Data!E2:E4274="T1")*(Data!J2:J4274="FEMALE")*(Data!K2:L4274="FEMALE")*(Data!C2:C4274="Successful")) -> 25 | D115: =IF(B115>0,C115/B115,0) -> 0.6097561 | E115: =SUMPRODUCT((Data!E2:E4274="T1")*(Data!J2:J4274="FEMALE")*(Data!K2:L4274="FEMALE")*(Data!C2:C4274="Not successful")) -> 8 | F115: =IF(B115>0,E115/B115,0) -> 0.19512195 | G115: =SUMPRODUCT((Data!E2:E4274="T1")*(Data!J2:J4274="FEMALE")*(Data!K2:L4274="FEMALE")*(Data!C2:C4274="Asleep")) -> 8 | H115: =IF(B115>0,G115/B115,0) -> 0.19512195
A117: T2: Urban planning & neighbourhood issues
A118: Gender combo | B118: Total | C118: Successful | D118: % Successful | E118: Not successful | F118: % Not succ. | G118: Asleep | H118: % Asleep
A119: Male req. → Male resp. | B119: =SUMPRODUCT((Data!E2:E4274="T2")*(Data!J2:J4274="MALE")*(Data!K2:L4274="MALE")) -> 78 | C119: =SUMPRODUCT((Data!E2:E4274="T2")*(Data!J2:J4274="MALE")*(Data!K2:L4274="MALE")*(Data!C2:C4274="Successful")) -> 41 | D119: =IF(B119>0,C119/B119,0) -> 0.52564103 | E119: =SUMPRODUCT((Data!E2:E4274="T2")*(Data!J2:J4274="MALE")*(Data!K2:L4274="MALE")*(Data!C2:C4274="Not successful")) -> 18 | F119: =IF(B119>0,E119/B119,0) -> 0.23076923 | G119: =SUMPRODUCT((Data!E2:E4274="T2")*(Data!J2:J4274="MALE")*(Data!K2:L4274="MALE")*(Data!C2:C4274="Asleep")) -> 19 | H119: =IF(B119>0,G119/B119,0) -> 0.24358974
A120: Male req. → Female resp. | B120: =SUMPRODUCT((Data!E2:E4274="T2")*(Data!J2:J4274="MALE")*(Data!K2:L4274="FEMALE")) -> 71 | C120: =SUMPRODUCT((Data!E2:E4274="T2")*(Data!J2:J4274="MALE")*(Data!K2:L4274="FEMALE")*(Data!C2:C4274="Successful")) -> 52 | D120: =IF(B120>0,C120/B120,0) -> 0.73239437 | E120: =SUMPRODUCT((Data!E2:E4274="T2")*(Data!J2:J4274="MALE")*(Data!K2:L4274="FEMALE")*(Data!C2:C4274="Not successful")) -> 14 | F120: =IF(B120>0,E120/B120,0) -> 0.1971831 | G120: =SUMPRODUCT((Data!E2:E4274="T2")*(Data!J2:J4274="MALE")*(Data!K2:L4274="FEMALE")*(Data!C2:C4274="Asleep")) -> 5 | H120: =IF(B120>0,G120/B120,0) -> 0.070422535
A121: Female req. → Male resp. | B121: =SUMPRODUCT((Data!E2:E4274="T2")*(Data!J2:J4274="FEMALE")*(Data!K2:L4274="MALE")) -> 43 | C121: =SUMPRODUCT((Data!E2:E4274="T2")*(Data!J2:J4274="FEMALE")*(Data!K2:L4274="MALE")*(Data!C2:C4274="Successful")) -> 21 | D121: =IF(B121>0,C121/B121,0) -> 0.48837209 | E121: =SUMPRODUCT((Data!E2:E4274="T2")*(Data!J2:J4274="FEMALE")*(Data!K2:L4274="MALE")*(Data!C2:C4274="Not successful")) -> 12 | F121: =IF(B121>0,E121/B121,0) -> 0.27906977 | G121: =SUMPRODUCT((Data!E2:E4274="T2")*(Data!J2:J4274="FEMALE")*(Data!K2:L4274="MALE")*(Data!C2:C4274="Asleep")) -> 10 | H121: =IF(B121>0,G121/B121,0) -> 0.23255814
A122: Female req. → Female resp. | B122: =SUMPRODUCT((Data!E2:E4274="T2")*(Data!J2:J4274="FEMALE")*(Data!K2:L4274="FEMALE")) -> 31 | C122: =SUMPRODUCT((Data!E2:E4274="T2")*(Data!J2:J4274="FEMALE")*(Data!K2:L4274="FEMALE")*(Data!C2:C4274="Successful")) -> 18 | D122: =IF(B122>0,C122/B122,0) -> 0.58064516 | E122: =SUMPRODUCT((Data!E2:E4274="T2")*(Data!J2:J4274="FEMALE")*(Data!K2:L4274="FEMALE")*(Data!C2:C4274="Not successful")) -> 6 | F122: =IF(B122>0,E122/B122,0) -> 0.19354839 | G122: =SUMPRODUCT((Data!E2:E4274="T2")*(Data!J2:J4274="FEMALE")*(Data!K2:L4274="FEMALE")*(Data!C2:C4274="Asleep")) -> 7 | H122: =IF(B122>0,G122/B122,0) -> 0.22580645
A124: T3: Police & administrative authority legality
...
